generator/__init__.py
Random_string_password-0.1.dist-info/LICENCE.txt
Random_string_password-0.1.dist-info/METADATA
Random_string_password-0.1.dist-info/WHEEL
Random_string_password-0.1.dist-info/top_level.txt
Random_string_password-0.1.dist-info/RECORD
